Workbook
Name aporte: Folha1!$C$19:$C$19
Name patrimonio: Folha1!$C$22:$C$22
Name qtd_anos: Folha1!$C$20:$C$20
Name rendimento_carteira: Folha1!$C$14:$C$14
Name salario: Folha1!$C$13:$C$13
Name sugestao_investimento: Folha1!$C$15:$C$15
Name taxa_mensal: Folha1!$C$21:$C$21

Sheet Folha1
B12: CONFIGURAÇÕES
B13: Salário | C13: 5000
B14: Rendimento Carteira | C14: 0.006
B15: Sugestão de Investimento | C15: =C13*30% -> 1500
B18: Investimento Mensal
B19: Quanto investir por mês? | C19: 500
B20: Por Quantos Anos? | C20: 5
B21: Taxa de Rendimento Mensal | C21: 0.01079
B22: Patrimônio acumulado | C22: {=FV(taxa_mensal,qtd_anos*12,aporte*-1)} -> 41888.457
B23: Dividendos Mensais? | C23: {=patrimonio*rendimento_carteira} -> 251.33074
B25: Cenários | D25: Dividendo
A26: 2 | B26: Quanto em 2 Anos? | C26: =FV($C$21,$A26*12,$C$19*-1) -> 13613.814 | D26: {=C26*rendimento_carteira} -> 81.682882
A27: 5 | B27: Quanto em 5 Anos? | C27: =FV($C$21,$A27*12,$C$19*-1) -> 41888.457 | D27: {=C27*rendimento_carteira} -> 251.33074
A28: 10 | B28: Quanto em 10 anos ? | C28: =FV($C$21,$A28*12,$C$19*-1) -> 121642.11 | D28: {=C28*rendimento_carteira} -> 729.85264
A29: 20 | B29: Quanto em 20 anos? | C29: =FV($C$21,$A29*12,$C$19*-1) -> 562599.2 | D29: {=C29*rendimento_carteira} -> 3375.5952
A30: 30 | B30: Quanto em 30 Anos? | C30: =FV($C$21,$A30*12,$C$19*-1) -> 2161084.8 | D30: {=C30*rendimento_carteira} -> 12966.509
B34: PERFIL | C34: Moderado
B35: VALOR A SER INVESTIDO POR MÊS | C35: {=aporte} -> 500
B37: TIPO DE FII | C37: Percentual Sugerido | D37: Valores
B38: PAPEL | C38: =VLOOKUP($C$34&"-"&B38,Folha2!$A:$D,4,FALSE) -> 0.32 | D38: =C38*$C$35 -> 160
B39: TIJOLO | C39: =VLOOKUP($C$34&"-"&B39,Folha2!$A:$D,4,FALSE) -> 0.35 | D39: =C39*$C$35 -> 175
B40: HÍBRIDOS | C40: =VLOOKUP($C$34&"-"&B40,Folha2!$A:$D,4,FALSE) -> 0.08 | D40: =C40*$C$35 -> 40
B41: FOFs | C41: =VLOOKUP($C$34&"-"&B41,Folha2!$A:$D,4,FALSE) -> 0.05 | D41: =C41*$C$35 -> 25
B42: DESENVOLVIMENTO | C42: =VLOOKUP($C$34&"-"&B42,Folha2!$A:$D,4,FALSE) -> 0.1 | D42: =C42*$C$35 -> 50
B43: HOTELARIAS | C43: =VLOOKUP($C$34&"-"&B43,Folha2!$A:$D,4,FALSE) -> 0.1 | D43: =C43*$C$35 -> 50
D44: =SUM(D38:D43) -> 500

Sheet Folha2
A2: CHAVE | B2: PERFIL | C2: TIPOS DE FII | D2: %
A3: =$B$3&"-"&C3 -> Conservador-PAPEL | B3: Conservador | C3: PAPEL | D3: 0.3
A4: =$B$3&"-"&C4 -> Conservador-TIJOLO | B4: Conservador | C4: TIJOLO | D4: 0.5
A5: =$B$3&"-"&C5 -> Conservador-HÍBRIDOS | B5: Conservador | C5: HÍBRIDOS | D5: 0.1 | G5: Moderado-TIJOLO | H5: =VLOOKUP(G5,$A:$D,4,FALSE) -> 0.35
A6: =$B$3&"-"&C6 -> Conservador-FOFs | B6: Conservador | C6: FOFs | D6: 0.1
A7: =$B$3&"-"&C7 -> Conservador-DESENVOLVIMENTO | B7: Conservador | C7: DESENVOLVIMENTO | D7: 0
A8: =$B$3&"-"&C8 -> Conservador-HOTELARIAS | B8: Conservador | C8: HOTELARIAS | D8: 0
A9: =$B$9&"-"&C9 -> Moderado-PAPEL | B9: Moderado | C9: PAPEL | D9: 0.32
A10: =$B$9&"-"&C10 -> Moderado-TIJOLO | B10: Moderado | C10: TIJOLO | D10: 0.35
A11: =$B$9&"-"&C11 -> Moderado-HÍBRIDOS | B11: Moderado | C11: HÍBRIDOS | D11: 0.08
A12: =$B$9&"-"&C12 -> Moderado-FOFs | B12: Moderado | C12: FOFs | D12: 0.05
A13: =$B$9&"-"&C13 -> Moderado-DESENVOLVIMENTO | B13: Moderado | C13: DESENVOLVIMENTO | D13: 0.1
A14: =$B$9&"-"&C14 -> Moderado-HOTELARIAS | B14: Moderado | C14: HOTELARIAS | D14: 0.1
A15: =B15&"-"&C15 -> Agressivo-PAPEL | B15: Agressivo | C15: PAPEL | D15: 0.5
A16: =B16&"-"&C16 -> Agressivo-TIJOLO | B16: Agressivo | C16: TIJOLO | D16: 0.1
A17: =B17&"-"&C17 -> Agressivo-HÍBRIDOS | B17: Agressivo | C17: HÍBRIDOS | D17: 0.05
A18: =B18&"-"&C18 -> Agressivo-FOFs | B18: Agressivo | C18: FOFs | D18: 0.05
A19: =B19&"-"&C19 -> Agressivo-DESENVOLVIMENTO | B19: Agressivo | C19: DESENVOLVIMENTO | D19: 0.2
A20: =B20&"-"&C20 -> Agressivo-HOTELARIAS | B20: Agressivo | C20: HOTELARIAS | D20: 0.1
